findmydevice/__init__.py
findmydevice/admin_views.py
findmydevice/apps.py
findmydevice/checks.py
findmydevice/constants.py
findmydevice/context_processors.py
findmydevice/exceptions.py
findmydevice/json_utils.py
findmydevice/urls.py
findmydevice/admin/__init__.py
findmydevice/admin/device.py
findmydevice/admin/fmd_admin_site.py
findmydevice/admin/location.py
findmydevice/admin/mixins.py
findmydevice/admin/picture.py
findmydevice/client/__init__.py
findmydevice/client/__main__.py
findmydevice/client/client.py
findmydevice/client/constants.py
findmydevice/client/crypto.py
findmydevice/client/data_classes.py
findmydevice/client/tests/__init__.py
findmydevice/client/tests/test_client.py
findmydevice/client/tests/test_crypto.py
findmydevice/client/tests/fixtures/encrypted_location.txt
findmydevice/client/tests/fixtures/encrypted_private_key.txt
findmydevice/management/__init__.py
findmydevice/management/commands/__init__.py
findmydevice/management/commands/fmd.py
findmydevice/management/commands/run_dev_server.py
findmydevice/migrations/0001_initial.py
findmydevice/migrations/0002_alter_location_raw_date.py
findmydevice/migrations/0003_rename_deviceuser_device.py
findmydevice/migrations/0004_device_name.py
findmydevice/migrations/0005_user_agent.py
findmydevice/migrations/0006_push_commands.py
findmydevice/migrations/0007_editable.py
findmydevice/migrations/0008_device_short_id.py
findmydevice/migrations/0009_bigger_keys.py
findmydevice/migrations/0010_expand_field_length.py
findmydevice/migrations/0011_recreate_location.py
findmydevice/migrations/0012_alter_device_hashed_password_alter_device_name.py
findmydevice/migrations/0013_remove_device_command2user_device_command_data.py
findmydevice/migrations/0014_picture.py
findmydevice/migrations/0015_alter_picture_data.py
findmydevice/migrations/__init__.py
findmydevice/models/__init__.py
findmydevice/models/base.py
findmydevice/models/device.py
findmydevice/models/location.py
findmydevice/models/picture.py
django_fmd-0.9.2.dist-info/METADATA
django_fmd-0.9.2.dist-info/WHEEL
django_fmd-0.9.2.dist-info/entry_points.txt
django_fmd-0.9.2.dist-info/licenses/AUTHORS
django_fmd-0.9.2.dist-info/licenses/LICENSE
django_fmd-0.9.2.dist-info/RECORD
