Metadata-Version: 2.4
Name: django-fmd
Version: 0.9.2
Summary: Server for 'Find My Device' android app, implemented in Django/Python
Project-URL: Documentation, https://gitlab.com/jedie/django-find-my-device
Project-URL: Source, https://gitlab.com/jedie/django-find-my-device
Author-email: Jens Diemer <git@jensdiemer.de>
License: GPL-3.0-or-later
License-File: AUTHORS
License-File: LICENSE
Requires-Python: >=3.11
Requires-Dist: argon2-cffi
Requires-Dist: bx-django-utils
Requires-Dist: bx-py-utils
Requires-Dist: colorlog
Requires-Dist: django
Requires-Dist: django-debug-toolbar
Requires-Dist: gunicorn
Requires-Dist: pycryptodomex
Requires-Dist: requests
